
{
    "listen_addr": "0.0.0.0",
    "listen_port": 5445,
    "static_resources": "resources",
    "sqlite3_database": "~/.webdisk/wd.db",
    "allow_http_redirect": true,

    "filesystem": {
        "type": "multi",
        "data": [
            {
                "srcPrefix": "/home/prack/mydisk/alioss/",
                "dstPrefix": "/",
                "config": {
                    "type": "alioss",
                    "data": {
                        "region": "oss-cn-beijing",
                        "accessKeyId": "LTAI4G1Vvb98cMGwDNyz1nsp",
                        "accessKeySecret": "tMNv7f5MWkPn2SfiUJ8dEpSwWB3BSY",
                        "bucket": "helloldy",
                        "secure": true
                    }
                }
            },
            {
                "srcPrefix": "/",
                "dstPrefix": "/",
                "config": {
                    "type": "local"
                }
            }
        ]
    }
}

